MANIFEST.in
README.markdown
setup.py
pyblosxommtimecache/__init__.py
pyblosxommtimecache.egg-info/PKG-INFO
pyblosxommtimecache.egg-info/SOURCES.txt
pyblosxommtimecache.egg-info/dependency_links.txt
pyblosxommtimecache.egg-info/requires.txt
pyblosxommtimecache.egg-info/top_level.txt