Metadata-Version: 1.1
Name: pyblosxommtimecache
Version: 0.0.2
Summary: A Pyblosxom filestat plugin that caches the mtimes of your entries in a .mtimes.yaml file.
Home-page: https://github.com/seanh/pyblosxommtimecache
Author: Sean Hammond
Author-email: pyblosxommtimecache@seanh.cc
License: GPLv3
Keywords: pyblosxom
Platform: UNKNOWN
Classifier: Development Status :: 3 - Alpha
Classifier: License :: OSI Approved :: GNU General Public License v3 (GPLv3)
Classifier: Programming Language :: Python :: 2.7
